rapid_api_client/__init__.py
rapid_api_client/annotations.py
rapid_api_client/client.py
rapid_api_client/decorator.py
rapid_api_client/errors.py
rapid_api_client/parameters.py
rapid_api_client/py.typed
rapid_api_client/response.py
rapid_api_client/utils.py
rapid_api_client/xml.py
rapid_api_client-0.9.0.dist-info/WHEEL
rapid_api_client-0.9.0.dist-info/METADATA
rapid_api_client-0.9.0.dist-info/RECORD
