Metadata-Version: 2.3
Name: rapid-api-client
Version: 0.9.0
Summary: Rapidly develop your API clients using decorators and annotations
Author: Sébastien MB
Author-email: Sébastien MB <seb@essembeh.org>
Classifier: Development Status :: 4 - Beta
Classifier: Environment :: Web Environment
Classifier: Framework :: AsyncIO
Classifier: Framework :: Pydantic
Classifier: Intended Audience :: Developers
Classifier: License :: OSI Approved :: MIT License
Classifier: Operating System :: OS Independent
Classifier: Programming Language :: Python :: 3 :: Only
Classifier: Programming Language :: Python :: 3.10
Classifier: Programming Language :: Python :: 3.11
Classifier: Programming Language :: Python :: 3.12
Classifier: Programming Language :: Python :: 3.13
Classifier: Topic :: Internet :: WWW/HTTP
Classifier: Topic :: Software Development :: Libraries :: Python Modules
Classifier: Topic :: Utilities
Classifier: Typing :: Typed
Requires-Dist: httpx>=0.27,<1.0
Requires-Dist: pydantic>=2.10,<3.0
Requires-Python: >=3.10
Project-URL: Homepage, https://github.com/essembeh/rapid-api-client
Project-URL: Issues, https://github.com/essembeh/rapid-api-client/issues
Project-URL: Repository, https://github.com/essembeh/rapid-api-client
